carton_forklift/__init__.py
carton_forklift/py.typed
carton_forklift-0.1.0.dist-info/WHEEL
carton_forklift-0.1.0.dist-info/METADATA
carton_forklift-0.1.0.dist-info/RECORD
