Metadata-Version: 2.3
Name: carton-forklift
Version: 0.1.0
Summary: ForkLift by Carton, a data processing framework for Machine Learning large scale datasets
Author: guipenedo
Author-email: guipenedo <nostrumg@gmail.com>
Requires-Python: >=3.10
